ham_cal/__init__.py
ham_cal/ham_cal.py
ham_cal-0.1.0.dist-info/METADATA
ham_cal-0.1.0.dist-info/WHEEL
ham_cal-0.1.0.dist-info/entry_points.txt
ham_cal-0.1.0.dist-info/top_level.txt
ham_cal-0.1.0.dist-info/RECORD
